setup.py
hspotipy/__init__.py
hspotipy/user.py
hspotipy.egg-info/PKG-INFO
hspotipy.egg-info/SOURCES.txt
hspotipy.egg-info/dependency_links.txt
hspotipy.egg-info/requires.txt
hspotipy.egg-info/top_level.txt