Metadata-Version: 1.0
Name: hspotipy
Version: 0.0.1
Summary: Spotify Music API
Home-page: https://github.com/zsdonghao/hspotipy
Author: HSpotipy Contributors
Author-email: dhsig552@163.com
License: apache
Keywords: Music,Spotipy
Platform: UNKNOWN
